setup.py
sentry_mattermost/__init__.py
sentry_mattermost/plugin.py
sentry_mattermost.egg-info/PKG-INFO
sentry_mattermost.egg-info/SOURCES.txt
sentry_mattermost.egg-info/dependency_links.txt
sentry_mattermost.egg-info/entry_points.txt
sentry_mattermost.egg-info/top_level.txt