Metadata-Version: 1.0
Name: sentry-mattermost
Version: 0.0.1
Summary: A Sentry plugin to send Mattermost notifications.
Home-page: https://github.com/NDrive/sentry-mattermost
Author: Andre Freitas
Author-email: andre.freitas@ndrive.com
License: MIT
Keywords: sentry mattermost devops
Platform: UNKNOWN
